GStiming/GS_timing.py
GStiming/__init__.py
GS_Timing-0.2.0.dist-info/METADATA
GS_Timing-0.2.0.dist-info/WHEEL
GS_Timing-0.2.0.dist-info/top_level.txt
GS_Timing-0.2.0.dist-info/RECORD
