Metadata-Version: 2.1
Name: GS-Timing
Version: 0.2.0
Summary: Better timing resolution on Win and Linux
Home-page: UNKNOWN
Author: Gabriel Staples
Author-email: UNKNOWN
License: UNKNOWN
Platform: UNKNOWN
